{"cameraMode":{"drawMode":0,"name":"Shaded","section":"Shading Mode"},"sceneLighting":true,"audioPlay":false,"sceneViewState":{"m_AlwaysRefresh":false,"showFog":true,"showSkybox":true,"showFlares":true,"showImageEffects":true,"showParticleSystems":true,"showVisualEffectGraphs":true,"m_FxEnabled":true},"in2DMode":false,"pivot":{"x":-32.59503936767578,"y":22.074975967407228,"z":-24.35886001586914},"rotation":{"x":-0.1126788854598999,"y":-0.8373831510543823,"z":0.5005954504013062,"w":-0.1884777992963791},"size":38.09361267089844,"orthographic":false}